autodocmiashs/__init__.py
autodocmiashs/cli.py
autodocmiashs/generator.py
autodocmiashs-0.1.0.dist-info/METADATA
autodocmiashs-0.1.0.dist-info/WHEEL
autodocmiashs-0.1.0.dist-info/entry_points.txt
autodocmiashs-0.1.0.dist-info/top_level.txt
autodocmiashs-0.1.0.dist-info/RECORD
