Metadata-Version: 2.4
Name: autodocmiashs
Version: 0.1.0
Summary: One-command docstring generator using Mistral (Google-style) for MIASHS students
Author: Aness Rabia
Requires-Python: >=3.9
Requires-Dist: requests
